mimic_video/__init__.py
mimic_video/cosmos_predict.py
mimic_video/mimic_video.py
mimic_video-0.0.48.dist-info/METADATA
mimic_video-0.0.48.dist-info/WHEEL
mimic_video-0.0.48.dist-info/licenses/LICENSE
mimic_video-0.0.48.dist-info/RECORD
