Metadata-Version: 2.4
Name: mimic-video
Version: 0.0.48
Summary: Mimic Video
Project-URL: Homepage, https://pypi.org/project/mimic-video/
Project-URL: Repository, https://github.com/lucidrains/mimic-video
Author-email: Phil Wang <lucidrains@gmail.com>
License: MIT License
License-File: LICENSE
Keywords: artificial intelligence,attention mechanism,deep learning,video language action model
Classifier: Development Status :: 4 - Beta
Classifier: Intended Audience :: Developers
Classifier: License :: OSI Approved :: MIT License
Classifier: Programming Language :: Python :: 3.10
Classifier: Topic :: Scientific/Engineering :: Artificial Intelligence
Requires-Python: >=3.10
Requires-Dist: einops>=0.8.1
Requires-Dist: einx>=0.3.0
Requires-Dist: hyper-connections>=0.4.3
Requires-Dist: peft
Requires-Dist: torch-einops-utils>=0.0.17
Requires-Dist: torch>=2.5
Requires-Dist: tqdm
Requires-Dist: x-mlps-pytorch
Provides-Extra: examples
Provides-Extra: test
Requires-Dist: accelerate; extra == 'test'
Requires-Dist: diffusers>=0.32.0; extra == 'test'
Requires-Dist: pytest; extra == 'test'
Requires-Dist: transformers; extra == 'test'
